setup.py
zeph/__init__.py
zeph.egg-info/PKG-INFO
zeph.egg-info/SOURCES.txt
zeph.egg-info/dependency_links.txt
zeph.egg-info/not-zip-safe
zeph.egg-info/pbr.json
zeph.egg-info/top_level.txt