Metadata-Version: 1.0
Name: zeph
Version: 0.0.1
Summary: Geographic arrays in Python
Home-page: https://github.com/vitale232/zeph
Author: Charles Morton and Andrew Vitale
Author-email: Andrew.Vitale@DRI.edu
License: MIT
Platform: UNKNOWN
